{"id":"htc_066","name":"酸奶意式奶冻","cat":"dessert","catLabel":"甜品","time":30,"difficulty":4,"tagline":"![酸奶意式奶冻-预览图-1](./酸奶意式奶冻.png…","desc":"![酸奶意式奶冻-预览图-1](./酸奶意式奶冻.png)\r\r一道改良自意大利经典的甜品，融入原味酸奶后口感更为清爽顺滑，甜而不腻，适合作为餐后小点搭配水果或果酱。奶制品带来丰富的钙质和蛋白质，营养温和。制作步骤简单，只需加热搅拌和冷藏定型，新手也能顺利上手，从准备到冷藏完成大约需要 5 小时。\r\r预估烹饪难度：★★★★\r\r预估卡路里：1034 大卡\r\r## 必备原料和工具\r\r- 淡奶油\r- 糖\r- 原味酸奶\r- 吉利丁片\r- 筛网\r\r## 计算\r\r每次制作前需要确定计划做几份。一份正好够 3-6 个人吃。\r\r每份：\r\r- 淡奶油 200g\r- 糖 40g\r- 原味酸奶 250g\r- 吉利丁片 6g\r\r## 操作\r\r1. 吉利丁片剪成小片，泡入冷水中\r2. 淡奶油和糖放入锅中，加热至 60 度\r3. 关火，吉利丁从水中取出，控干水份，加入热淡奶油中，搅拌均匀\r4. 淡奶油降温至 40 度，","ingredients":["每次制作前需要确定计划做几份。一份正好够 3-6 个人吃。","淡奶油 200g","糖 40g","原味酸奶 250g","吉利丁片 6g"],"steps":["吉利丁片剪成小片，泡入冷水中","淡奶油和糖放入锅中，加热至 60 度","关火，吉利丁从水中取出，控干水份，加入热淡奶油中，搅拌均匀","淡奶油降温至 40 度，加入原味酸奶，搅拌均匀","将上述步骤得到的混合物过两遍筛网","分装入合适的容器，放入冰箱冷藏 4 小时以上"],"tip":"传统版本的意式奶冻只用淡奶油，且糖量更大，比较甜腻。此版本做了改良，吃起来负担更小。","img":"htc_066.jpg"}