{"id":"htc_181","name":"香干肉丝","cat":"meat","catLabel":"荤菜","time":30,"difficulty":3,"tagline":"香干肉丝是一道咸香下饭的家常小炒，肉丝嫩滑，香干柔韧，青…","desc":"香干肉丝是一道咸香下饭的家常小炒，肉丝嫩滑，香干柔韧，青椒爽脆。富含动物性与植物性双重蛋白质，搭配青椒补充维生素。难度适中，新手稍加练习即可掌握，预计制作时长约 30 分钟。\r\r预估烹饪难度：★★★\r\r预估卡路里：472 大卡\r\r## 必备原料和工具\r\r* 猪里脊（可以买超市切好且称重好的肉丝）\r* 香干\r* 盐\r* 生抽\r* 淀粉\r* 大蒜\r* 青椒\r* 鸡精\r\r## 计算\r\r每次制作前需要确定计划做几份。一份正好够 1 个人食用\r\r总量：\r\r* 香干 = 份数 * 75g\r* 青椒的数量 = 份数 * 5 个\r* 肉量 = 份数 * 100g\r* 盐量 = 份数 * 3g\r* 生抽 = 份数 * 5ml\r* 淀粉 = 份数 * 5g\r* 大蒜 = 份数 * 5g（大约 3 个蒜瓣）\r* 鸡精 = 2g\r\r使用上述条件，计算出计划使用的原材料比例。\r\r## 操作\r\r### 准备工作\r\r1","ingredients":["每次制作前需要确定计划做几份。一份正好够 1 个人食用","总量：","香干 = 份数  75g","青椒的数量 = 份数  5 个","肉量 = 份数  100g","盐量 = 份数  3g","生抽 = 份数  5ml","淀粉 = 份数  5g","大蒜 = 份数  5g","鸡精 = 2g","使用上述条件，计算出计划使用的原材料比例。"],"steps":["`肉丝`（没有肉丝，自己切）用生抽(3ml)，生粉混合均匀待用。","将`青椒`洗净，再用`滚刀手法`切好备用。","`大蒜`横切成片，`香干`切丝。","`淀粉`与水(10ml)混合，搅拌均匀。","干净锅 15ml 油，不用等油热就倒入肉丝慢慢划散，肉丝熟了，立马捞出，留油到锅里。","将蒜片和香干放入锅中，加入 2ml 生抽，翻炒均匀。","2-3 分钟，看火大小，将青椒丝放入锅中混合，翻炒。","1 分钟后，放入肉丝混合。","倒入淀粉与水的混合物勾芡，加入盐 3g，鸡精 2g，翻炒 2-3 分钟出锅。","成品。注意，不同的锅具或者灶台，会影响翻炒的时间，建议，不确定是否熟了，可以试吃下。"],"tip":"辣椒选择青椒，螺丝椒为最优解，喜欢辣的可以加入小米椒切细碎，同青椒一起加入！","img":"htc_181.jpg"}