{"id":"htc_153","name":"奶酪培根通心粉","cat":"meat","catLabel":"荤菜","time":30,"difficulty":3,"tagline":"![烘烤成品](./oven.jpg)\r![非烘烤成品]…","desc":"![烘烤成品](./oven.jpg)\r![非烘烤成品](./onepot.png)\r\r奶酪培根通心粉是经典美式家常菜，口感浓郁绵密，奶酪包裹弹牙通心粉，搭配香脆培根，咸香满足。富含蛋白质与钙质，但热量和脂肪较高，建议偶尔享用。制作需要一定耐心，掌握基础白酱和火候对新手略有挑战，整体难度中等。不烘烤时约 30 分钟即可上桌，若选择烘烤需额外预热和烤制，总时长约 1 小时。\r\r预估烹饪难度：★★★\r\r预估卡路里：728 大卡\r\r## 必备原料和工具\r\r- 通心粉\r- 奶酪\r- 肉类\r- 洋葱\r- 黄油\r- 面粉\r- 牛奶\r- 大蒜\r\r## 计算\r\r每次制作前需要确定计划做几份。一份正好够 2 个人吃。\r\r- 通心粉 100-125g\r- 奶酪 40-55g，若要烘烤额外准备 25g， 条状\r- 培根或其他肉类 100-125g\r- 洋葱 25g-40g 切成碎\r- 黄油 15g\r- 面粉 1","ingredients":["每次制作前需要确定计划做几份。一份正好够 2 个人吃。","通心粉 100-125g","奶酪 40-55g，若要烘烤额外准备 25g， 条状","培根或其他肉类 100-125g","洋葱 25g-40g 切成碎","黄油 15g","面粉 10g","牛奶 125ml","大蒜半瓣，切碎"],"steps":["奶酪要磨成碎末","洋葱切成条状","通心粉用微咸的水煮 6 分钟","**中火**","锅中放入黄油，等待融化","加入洋葱","洋葱软化后加入大蒜","大蒜香味出来后，加入肉类，等待 5 秒","**小火**","分四次加入牛奶，每次搅拌 5 秒后再加下一次","加入面粉并充分搅拌","加入奶酪并搅拌均匀","将通心粉和奶酪搅拌","如果不打算烘烤，可以直接吃了","**烘烤：**","预热烤箱至 180°C","将额外的 50g 芝士铺在通心粉之上","等待烤箱预热至 180°C 后，将通心粉放入","烤至表面金黄,约 24 分钟"],"tip":"本料理及其不健康，有大约 1300 大卡，80g 脂肪，不建议常吃。","img":"htc_153.jpg"}